spatgen/__init__.py
spatgen/__main__.py
spatgen/parser.py
spatgen-0.1.6.dist-info/LICENSE
spatgen-0.1.6.dist-info/METADATA
spatgen-0.1.6.dist-info/WHEEL
spatgen-0.1.6.dist-info/top_level.txt
spatgen-0.1.6.dist-info/RECORD
