Metadata-Version: 2.1
Name: spatgen
Version: 0.1.6
Summary: Pattern generating DSL for spaCy
Home-page: https://github.com/dailyedit/spatgen
Author: Stephen Pegoraro
Author-email: steve@dailyedit.com
License: MIT
Project-URL: Source, https://github.com/dailyedit/spatgen
Project-URL: Bug Tracker, https://github.com/dailyedit/spatgen/issues
Platform: UNKNOWN
Classifier: Development Status :: 3 - Alpha
Classifier: Intended Audience :: Developers
Classifier: Intended Audience :: Science/Research
Classifier: Topic :: Software Development :: Libraries
Classifier: Topic :: Software Development :: Code Generators
Classifier: Programming Language :: Python :: 3
Classifier: License :: OSI Approved :: MIT License
Classifier: Operating System :: OS Independent
Requires-Python: >=3.6
License-File: LICENSE
Requires-Dist: lark (>=1.0.0)
